canister.py
canister-1.5.2.data/scripts/canister.py
canister-1.5.2.dist-info/LICENSE
canister-1.5.2.dist-info/METADATA
canister-1.5.2.dist-info/WHEEL
canister-1.5.2.dist-info/top_level.txt
canister-1.5.2.dist-info/RECORD
